spark_dynamic_flatten/__init__.py
spark_dynamic_flatten/flatten.py
spark_dynamic_flatten/tree.py
spark_dynamic_flatten/tree_flatten.py
spark_dynamic_flatten/tree_manager.py
spark_dynamic_flatten/tree_schema.py
spark_dynamic_flatten/utils.py
spark_dynamic_flatten-1.2.4.dist-info/LICENSE
spark_dynamic_flatten-1.2.4.dist-info/METADATA
spark_dynamic_flatten-1.2.4.dist-info/WHEEL
spark_dynamic_flatten-1.2.4.dist-info/RECORD
