Metadata-Version: 2.3
Name: spark-dynamic-flatten
Version: 1.2.4
Summary: Tools for pyspark dataframes to dynamically flatten based on configuration and compare schemas
License: MIT
Author: Hartmut Koepf
Requires-Python: >=3.8
Classifier: License :: OSI Approved :: MIT License
Classifier: Programming Language :: Python :: 3
Classifier: Programming Language :: Python :: 3.8
Classifier: Programming Language :: Python :: 3.9
Classifier: Programming Language :: Python :: 3.10
Classifier: Programming Language :: Python :: 3.11
Classifier: Programming Language :: Python :: 3.12
Classifier: Programming Language :: Python :: 3.13
Requires-Dist: pyspark (>=3.5.0,<4.0.0)
